acceptChanges.py
acceptchanges-1.1.dist-info/licenses/LICENSE
acceptchanges-1.1.dist-info/METADATA
acceptchanges-1.1.dist-info/WHEEL
acceptchanges-1.1.dist-info/entry_points.txt
acceptchanges-1.1.dist-info/top_level.txt
acceptchanges-1.1.dist-info/RECORD
