Metadata-Version: 2.4
Name: acceptChanges
Version: 1.1
Summary: Module for accepting all changes to LaTeX source marked using the package `changes`
Author-email: Erkka Rinne <erkka.rinne@fmi.fi>
License: MIT License
Project-URL: repository, https://github.com/pandas-dev/pandas
Classifier: Programming Language :: Python :: 3
Classifier: License :: OSI Approved :: MIT License
Classifier: Operating System :: OS Independent
Classifier: Topic :: Text Processing :: Markup :: LaTeX
Requires-Python: >=3.6
License-File: LICENSE
Requires-Dist: pylatexenc~=2.10
Dynamic: license-file
